cv_pipeliner/__init__.py
cv_pipeliner/batch_generators/__init__.py
cv_pipeliner/batch_generators/bbox_data.py
cv_pipeliner/batch_generators/image_data.py
cv_pipeliner/core/__init__.py
cv_pipeliner/core/batch_generator.py
cv_pipeliner/core/data.py
cv_pipeliner/core/data_converter.py
cv_pipeliner/core/inference_model.py
cv_pipeliner/core/inferencer.py
cv_pipeliner/data_converters/__init__.py
cv_pipeliner/data_converters/brickit.py
cv_pipeliner/data_converters/json.py
cv_pipeliner/data_converters/supervisely.py
cv_pipeliner/data_converters/yolo.py
cv_pipeliner/inference_models/__init__.py
cv_pipeliner/inference_models/classification/__init__.py
cv_pipeliner/inference_models/classification/core.py
cv_pipeliner/inference_models/classification/dummy.py
cv_pipeliner/inference_models/classification/tensorflow.py
cv_pipeliner/inference_models/detection/__init__.py
cv_pipeliner/inference_models/detection/core.py
cv_pipeliner/inference_models/detection/detectron2.py
cv_pipeliner/inference_models/detection/object_detection_api.py
cv_pipeliner/inference_models/detection/yolov5.py
cv_pipeliner/inference_models/detection/yolov8.py
cv_pipeliner/inference_models/embedder/__init__.py
cv_pipeliner/inference_models/embedder/core.py
cv_pipeliner/inference_models/embedder/pytorch.py
cv_pipeliner/inference_models/embedder/tensorflow.py
cv_pipeliner/inference_models/keypoints_regressor/__init__.py
cv_pipeliner/inference_models/keypoints_regressor/core.py
cv_pipeliner/inference_models/keypoints_regressor/mmpose.py
cv_pipeliner/inference_models/keypoints_regressor/tensorflow.py
cv_pipeliner/inference_models/keypoints_regressor/utils/LICENSE
cv_pipeliner/inference_models/keypoints_regressor/utils/__init__.py
cv_pipeliner/inference_models/keypoints_regressor/utils/mmpose_utils.py
cv_pipeliner/inference_models/pipeline.py
cv_pipeliner/inferencers/__init__.py
cv_pipeliner/inferencers/classification.py
cv_pipeliner/inferencers/detection.py
cv_pipeliner/inferencers/embedder.py
cv_pipeliner-0.21.1.dist-info/METADATA
cv_pipeliner-0.21.1.dist-info/WHEEL
cv_pipeliner-0.21.1.dist-info/licenses/LICENSE
cv_pipeliner-0.21.1.dist-info/RECORD
