Metadata-Version: 2.4
Name: cv_pipeliner
Version: 0.21.1
Summary: 
License-File: LICENSE
Author: bobokvsky
Author-email: alexander.kozlovsky.m@gmail.com
Requires-Python: >=3.9,<3.14
Classifier: Programming Language :: Python :: 3
Classifier: Programming Language :: Python :: 3.9
Classifier: Programming Language :: Python :: 3.10
Classifier: Programming Language :: Python :: 3.11
Classifier: Programming Language :: Python :: 3.12
Classifier: Programming Language :: Python :: 3.13
Requires-Dist: Pillow (>=8.0.0)
Requires-Dist: dataframe-image (>=0.1.1)
Requires-Dist: filterpy (>=1.4.5)
Requires-Dist: fsspec (>=2021.4.0)
Requires-Dist: imageio (>=2.17.0)
Requires-Dist: imutils (>=0.5.4)
Requires-Dist: joblib (>=1.0.1)
Requires-Dist: lxml (>=4.6.3)
Requires-Dist: matplotlib (>=3.4.1)
Requires-Dist: numpy (>=1.21.0,<2.0)
Requires-Dist: opencv-python (>=4.5.1.48)
Requires-Dist: pandas (>=1.2.4)
Requires-Dist: pathy (>=0.11.0)
Requires-Dist: pydantic (>=1.9.2)
Requires-Dist: requests (>=2.24.0)
Requires-Dist: scikit-image (>=0.18.3)
Requires-Dist: scikit_learn (>=0.24.2)
Requires-Dist: scipy (>=1.6.2)
Requires-Dist: tqdm (>=4.60.0)
